llamascript/__init__.py
llamascript-1.0.1.dist-info/LICENSE
llamascript-1.0.1.dist-info/METADATA
llamascript-1.0.1.dist-info/WHEEL
llamascript-1.0.1.dist-info/entry_points.txt
llamascript-1.0.1.dist-info/top_level.txt
llamascript-1.0.1.dist-info/RECORD
