Metadata-Version: 2.1
Name: llamascript
Version: 1.0.1
Summary: No-code AI chatbot using Ollama.
Home-page: https://github.com/Project-Llama/llamascript
Author: Zander Lewis
Author-email: zander@zanderlewis.dev
Classifier: Programming Language :: Python :: 3
Classifier: License :: OSI Approved :: MIT License
Classifier: Operating System :: OS Independent
Requires-Python: >=3.6
License-File: LICENSE
Requires-Dist: ollama
Requires-Dist: colorama
